aiolifx_connection/__init__.py
aiolifx_connection-1.0.0.dist-info/AUTHORS.rst
aiolifx_connection-1.0.0.dist-info/LICENSE
aiolifx_connection-1.0.0.dist-info/METADATA
aiolifx_connection-1.0.0.dist-info/WHEEL
aiolifx_connection-1.0.0.dist-info/top_level.txt
aiolifx_connection-1.0.0.dist-info/RECORD
