Metadata-Version: 2.1
Name: aiolifx-connection
Version: 1.0.0
Summary: A wrapper for aiolifx to connect to a single LIFX device
Home-page: https://github.com/bdraco/aiolifx_connection
Author: J. Nick Koston
Author-email: nick@koston.org
License: BSD license
Keywords: aiolifx_connection
Classifier: Development Status :: 2 - Pre-Alpha
Classifier: Intended Audience :: Developers
Classifier: License :: OSI Approved :: BSD License
Classifier: Natural Language :: English
Classifier: Programming Language :: Python :: 3
Classifier: Programming Language :: Python :: 3.6
Classifier: Programming Language :: Python :: 3.7
Classifier: Programming Language :: Python :: 3.8
Requires-Python: >=3.6
License-File: LICENSE
License-File: AUTHORS.rst
